Metadata-Version: 2.1
Name: easy-colorprint
Version: 0.1.2
Summary: Une librairie pour imprimer en couleur à l'écran
Author: Romain Dudek
License-File: LICENSE
